paginator/__init__.py
discord.py_paginator-1.5.0.dist-info/LICENSE
discord.py_paginator-1.5.0.dist-info/METADATA
discord.py_paginator-1.5.0.dist-info/WHEEL
discord.py_paginator-1.5.0.dist-info/top_level.txt
discord.py_paginator-1.5.0.dist-info/RECORD
