Metadata-Version: 2.1
Name: discord.py-paginator
Version: 1.5.0
Summary: A button & interactions pagination template for discord bots coded in discord.py
Home-page: https://github.com/Marseel-E/discord.py-paginator
Author: Marseel Eeso
Author-email: marseeleeso@gmail.com
License: UNKNOWN
Project-URL: Bug Tracker, https://github.com/Marseel-E/discord.py-paginator/issues
Platform: UNKNOWN
Classifier: Programming Language :: Python :: 3
Classifier: License :: OSI Approved :: MIT License
Classifier: Operating System :: OS Independent
Requires-Python: >=3.8
License-File: LICENSE
